twisties/__init__.py
twisties/__main__.py
twisties/scrambler.py
twisties/pickles/fto.pkl
twisties/pickles/mega_scrambler.pkl
twisties/pickles/pyra.pkl
twisties/pickles/scrambler133.pkl
twisties/pickles/scrambler222.pkl
twisties/pickles/scrambler223.pkl
twisties/pickles/scrambler333.pkl
twisties/pickles/scrambler444.pkl
twisties/pickles/skewb.pkl
twisties/pickles/sq1.pkl
twisties/pickles/util_scrambler.pkl
twisties-1.0.0.dist-info/LICENSE
twisties-1.0.0.dist-info/METADATA
twisties-1.0.0.dist-info/WHEEL
twisties-1.0.0.dist-info/top_level.txt
twisties-1.0.0.dist-info/RECORD
